slider_solver/__init__.py
slider_solver/solver.py
slider_solver-0.1.3.dist-info/METADATA
slider_solver-0.1.3.dist-info/WHEEL
slider_solver-0.1.3.dist-info/top_level.txt
slider_solver-0.1.3.dist-info/RECORD
