Metadata-Version: 2.4
Name: slider_solver
Version: 0.1.3
Summary: Universal Slider CAPTCHA Gap Detection
Home-page: https://github.com/yourusername/slider_solver
Author: MiChen
Author-email: rmcyyds@q.com
Classifier: Programming Language :: Python :: 3
Classifier: License :: OSI Approved :: MIT License
Requires-Python: >=3.8
Requires-Dist: opencv-python
Requires-Dist: numpy
Requires-Dist: Pillow
Dynamic: author
Dynamic: author-email
Dynamic: classifier
Dynamic: description
Dynamic: description-content-type
Dynamic: home-page
Dynamic: requires-dist
Dynamic: requires-python
Dynamic: summary
